global_py-0.0.1.dist-info/DESCRIPTION.rst
global_py-0.0.1.dist-info/METADATA
global_py-0.0.1.dist-info/RECORD
global_py-0.0.1.dist-info/WHEEL
global_py-0.0.1.dist-info/entry_points.txt
global_py-0.0.1.dist-info/metadata.json
global_py-0.0.1.dist-info/top_level.txt
globalpy/__init__.py
globalpy/global_setup.py
