Metadata-Version: 2.0
Name: global-py
Version: 0.0.1
Summary: Make your python scripts globally accessible!
Home-page: https://github.com/frankzl/globalpy
Author: Frank Lu
Author-email: frankz.lu@gmail.com
License: UNKNOWN
Platform: UNKNOWN
Classifier: Programming Language :: Python :: 3
Classifier: License :: OSI Approved :: MIT License
Classifier: Operating System :: OS Independent
